csv_batcher/__init__.py
csv_batcher/csv_pooler.py
csv_batcher/csv_splitter.py
csv_batcher/test_csv_pooler.py
csv_batcher/utils/logger.py
csv_batcher/utils/time.py
csv_batcher-0.1.6.dist-info/METADATA
csv_batcher-0.1.6.dist-info/WHEEL
csv_batcher-0.1.6.dist-info/RECORD
