Metadata-Version: 2.1
Name: csv-batcher
Version: 0.1.6
Summary: A python utility to split a large CSV into smaller ones, and uses multiprocessing to process the CSVs in parallel.
Home-page: https://pypi.org/project/csv-batcher/
License: Unlicense
Author: Steven Miers
Author-email: steven.miers@gmail.com
Requires-Python: >=3.12.2,<4.0.0
Classifier: License :: OSI Approved
Classifier: Programming Language :: Python :: 3
Requires-Dist: pandas (>=2.2.0,<3.0.0)
Project-URL: Documentation, https://tangledpath.github.io/csv-batcher
Project-URL: Repository, https://github.com/tangledpath/csv-batcher
